{
"type": "FeatureCollection",
"name": "fran",
"crs": { "type": "name", "properties": { "name": "urn:ogc:def:crs:OGC:1.3:CRS84" } },
"features": [
{ "type": "Feature", "properties": { "fid": 1 }, "geometry": { "type": "Point", "coordinates": [ 24.00402029, 49.83100056 ] } },
{ "type": "Feature", "properties": { "fid": 2 }, "geometry": { "type": "Point", "coordinates": [ 24.00396835, 49.83096641 ] } }
]
}
